[{"0":"20384","name":"BELL & HOWELL LLC BOWE BELL & HOWELL","invoice":"2021-12-31","gross":"1254.0800","status":"Paid","description":"Contracted Maintenance - Offic","alt":"6344420"},{"0":"20581","name":"BELL & HOWELL LLC BOWE BELL & HOWELL","invoice":"2021-12-31","gross":"3533.9800","status":"Paid","description":"Contracted Maintenance - Offic","alt":"6344420"},{"0":"20044","name":"BERKSHIRE SYSTEMS GROUP INC  ","invoice":"2021-12-29","gross":"4893.1100","status":"Paid","description":"Contracted Maintenance - Offic","alt":"6344420"},{"0":"19992","name":"PITNEY BOWES GLOBAL FINANCIAL SERVICES L ","invoice":"2021-12-18","gross":"1468.6500","status":"Paid","description":"Contracted Maintenance - Offic","alt":"6344420"},{"0":"20630","name":"QUADIENT  ","invoice":"2021-12-01","gross":"5851.9100","status":"Paid","description":"Contracted Maintenance - Offic","alt":"6344420"},{"0":"20026","name":"XEROX CORPORATION  ","invoice":"2021-12-01","gross":"50.0000","status":"Paid","description":"Contracted Maintenance - Offic","alt":"6344420"},{"0":"20025","name":"XEROX CORPORATION  ","invoice":"2021-12-01","gross":"186.6700","status":"Paid","description":"Contracted Maintenance - Offic","alt":"6344420"},{"0":"20024","name":"XEROX CORPORATION  ","invoice":"2021-12-01","gross":"50.0000","status":"Paid","description":"Contracted Maintenance - Offic","alt":"6344420"},{"0":"20577","name":"XEROX CORPORATION  ","invoice":"2021-12-04","gross":"1497.5400","status":"Paid","description":"Contracted Maintenance - Offic","alt":"6344420"},{"0":"21307","name":"XEROX CORPORATION  ","invoice":"2021-12-04","gross":"1008.0000","status":"Paid","description":"Contracted Maintenance - Offic","alt":"6344420"},{"0":"21306","name":"XEROX CORPORATION  ","invoice":"2021-12-04","gross":"1102.0000","status":"Paid","description":"Contracted Maintenance - Offic","alt":"6344420"},{"0":"21305","name":"XEROX CORPORATION  ","invoice":"2021-12-04","gross":"1629.0000","status":"Paid","description":"Contracted Maintenance - Offic","alt":"6344420"},{"0":"21304","name":"XEROX CORPORATION  ","invoice":"2021-12-04","gross":"3481.0000","status":"Paid","description":"Contracted Maintenance - Offic","alt":"6344420"},{"0":"21303","name":"XEROX CORPORATION  ","invoice":"2021-12-04","gross":"1384.0000","status":"Paid","description":"Contracted Maintenance - Offic","alt":"6344420"}]