[{"0":"16579","name":"POSTMASTER  ","invoice":"2021-04-23","gross":"25000.0000","status":"Paid","description":"Postage","alt":"6391010"},{"0":"16554","name":"UNITED PARCEL SERVICE  ","invoice":"2021-04-03","gross":"15.8900","status":"Paid","description":"Postage","alt":"6391010"},{"0":"17212","name":"UNITED PARCEL SERVICE  ","invoice":"2021-04-10","gross":"14.8700","status":"Paid","description":"Postage","alt":"6391010"},{"0":"17213","name":"UNITED PARCEL SERVICE  ","invoice":"2021-04-24","gross":"19.2600","status":"Paid","description":"Postage","alt":"6391010"},{"0":"16532","name":"UNITED PARCEL SERVICE  ","invoice":"2021-04-03","gross":"23.6300","status":"Paid","description":"Postage","alt":"6391010"},{"0":"16545","name":"UNITED PARCEL SERVICE  ","invoice":"2021-04-10","gross":"13.2000","status":"Paid","description":"Postage","alt":"6391010"},{"0":"16595","name":"UNITED PARCEL SERVICE  ","invoice":"2021-04-17","gross":"15.6600","status":"Paid","description":"Postage","alt":"6391010"},{"0":"17040","name":"UNITED PARCEL SERVICE  ","invoice":"2021-04-24","gross":"17.5500","status":"Paid","description":"Postage","alt":"6391010"}]