[{"0":"3614","name":"MID-ATLANTIC NEWSPAPER SERVICES INC  ","invoice":"2020-07-31","gross":"1532.5800","status":"Paid","description":"Advertising","alt":"6343200"},{"0":"3613","name":"MID-ATLANTIC NEWSPAPER SERVICES INC  ","invoice":"2020-07-31","gross":"7041.0600","status":"Paid","description":"Advertising","alt":"6343200"},{"0":"3612","name":"MID-ATLANTIC NEWSPAPER SERVICES INC  ","invoice":"2020-07-31","gross":"822.7800","status":"Paid","description":"Advertising","alt":"6343200"},{"0":"3611","name":"MID-ATLANTIC NEWSPAPER SERVICES INC  ","invoice":"2020-07-31","gross":"566.2500","status":"Paid","description":"Advertising","alt":"6343200"},{"0":"3610","name":"MID-ATLANTIC NEWSPAPER SERVICES INC  ","invoice":"2020-07-31","gross":"1223.8500","status":"Paid","description":"Advertising","alt":"6343200"},{"0":"3609","name":"MID-ATLANTIC NEWSPAPER SERVICES INC  ","invoice":"2020-07-31","gross":"1299.0000","status":"Paid","description":"Advertising","alt":"6343200"},{"0":"3608","name":"MID-ATLANTIC NEWSPAPER SERVICES INC  ","invoice":"2020-07-31","gross":"2925.4500","status":"Paid","description":"Advertising","alt":"6343200"},{"0":"3607","name":"MID-ATLANTIC NEWSPAPER SERVICES INC  ","invoice":"2020-07-31","gross":"1903.8600","status":"Paid","description":"Advertising","alt":"6343200"},{"0":"3606","name":"MID-ATLANTIC NEWSPAPER SERVICES INC  ","invoice":"2020-07-31","gross":"918.7500","status":"Paid","description":"Advertising","alt":"6343200"},{"0":"3605","name":"MID-ATLANTIC NEWSPAPER SERVICES INC  ","invoice":"2020-07-31","gross":"252.4700","status":"Paid","description":"Advertising","alt":"6343200"},{"0":"3604","name":"MID-ATLANTIC NEWSPAPER SERVICES INC  ","invoice":"2020-07-31","gross":"2283.3000","status":"Paid","description":"Advertising","alt":"6343200"},{"0":"3603","name":"MID-ATLANTIC NEWSPAPER SERVICES INC  ","invoice":"2020-07-31","gross":"6471.8600","status":"Paid","description":"Advertising","alt":"6343200"},{"0":"3602","name":"MID-ATLANTIC NEWSPAPER SERVICES INC  ","invoice":"2020-07-31","gross":"4408.2000","status":"Paid","description":"Advertising","alt":"6343200"},{"0":"3601","name":"MID-ATLANTIC NEWSPAPER SERVICES INC  ","invoice":"2020-07-31","gross":"404.2700","status":"Paid","description":"Advertising","alt":"6343200"},{"0":"3647","name":"MID-ATLANTIC NEWSPAPER SERVICES INC  ","invoice":"2020-07-31","gross":"2480.6300","status":"Paid","description":"Advertising","alt":"6343200"},{"0":"3646","name":"MID-ATLANTIC NEWSPAPER SERVICES INC  ","invoice":"2020-07-31","gross":"377.5000","status":"Paid","description":"Advertising","alt":"6343200"},{"0":"3645","name":"MID-ATLANTIC NEWSPAPER SERVICES INC  ","invoice":"2020-07-31","gross":"28812.0000","status":"Paid","description":"Advertising","alt":"6343200"},{"0":"3644","name":"MID-ATLANTIC NEWSPAPER SERVICES INC  ","invoice":"2020-07-31","gross":"33475.0000","status":"Paid","description":"Advertising","alt":"6343200"},{"0":"3643","name":"MID-ATLANTIC NEWSPAPER SERVICES INC  ","invoice":"2020-07-31","gross":"45390.0000","status":"Paid","description":"Advertising","alt":"6343200"},{"0":"3642","name":"MID-ATLANTIC NEWSPAPER SERVICES INC  ","invoice":"2020-07-31","gross":"12600.0000","status":"Paid","description":"Advertising","alt":"6343200"},{"0":"3641","name":"MID-ATLANTIC NEWSPAPER SERVICES INC  ","invoice":"2020-07-31","gross":"709.3800","status":"Paid","description":"Advertising","alt":"6343200"},{"0":"3640","name":"MID-ATLANTIC NEWSPAPER SERVICES INC  ","invoice":"2020-07-31","gross":"1740.3800","status":"Paid","description":"Advertising","alt":"6343200"},{"0":"3639","name":"MID-ATLANTIC NEWSPAPER SERVICES INC  ","invoice":"2020-07-31","gross":"1619.2500","status":"Paid","description":"Advertising","alt":"6343200"},{"0":"3638","name":"MID-ATLANTIC NEWSPAPER SERVICES INC  ","invoice":"2020-07-31","gross":"922.3500","status":"Paid","description":"Advertising","alt":"6343200"},{"0":"3637","name":"MID-ATLANTIC NEWSPAPER SERVICES INC  ","invoice":"2020-07-31","gross":"1197.0000","status":"Paid","description":"Advertising","alt":"6343200"},{"0":"3636","name":"MID-ATLANTIC NEWSPAPER SERVICES INC  ","invoice":"2020-07-31","gross":"1801.8000","status":"Paid","description":"Advertising","alt":"6343200"},{"0":"3635","name":"MID-ATLANTIC NEWSPAPER SERVICES INC  ","invoice":"2020-07-31","gross":"1578.9600","status":"Paid","description":"Advertising","alt":"6343200"},{"0":"3634","name":"MID-ATLANTIC NEWSPAPER SERVICES INC  ","invoice":"2020-07-31","gross":"1304.1000","status":"Paid","description":"Advertising","alt":"6343200"},{"0":"3633","name":"MID-ATLANTIC NEWSPAPER SERVICES INC  ","invoice":"2020-07-31","gross":"6362.2500","status":"Paid","description":"Advertising","alt":"6343200"},{"0":"3632","name":"MID-ATLANTIC NEWSPAPER SERVICES INC  ","invoice":"2020-07-31","gross":"2224.8800","status":"Paid","description":"Advertising","alt":"6343200"},{"0":"3631","name":"MID-ATLANTIC NEWSPAPER SERVICES INC  ","invoice":"2020-07-31","gross":"1968.0000","status":"Paid","description":"Advertising","alt":"6343200"},{"0":"3630","name":"MID-ATLANTIC NEWSPAPER SERVICES INC  ","invoice":"2020-07-31","gross":"4410.0000","status":"Paid","description":"Advertising","alt":"6343200"},{"0":"3629","name":"MID-ATLANTIC NEWSPAPER SERVICES INC  ","invoice":"2020-07-31","gross":"5994.3000","status":"Paid","description":"Advertising","alt":"6343200"},{"0":"3628","name":"MID-ATLANTIC NEWSPAPER SERVICES INC  ","invoice":"2020-07-31","gross":"3148.8000","status":"Paid","description":"Advertising","alt":"6343200"},{"0":"3627","name":"MID-ATLANTIC NEWSPAPER SERVICES INC  ","invoice":"2020-07-31","gross":"2572.9500","status":"Paid","description":"Advertising","alt":"6343200"},{"0":"3626","name":"MID-ATLANTIC NEWSPAPER SERVICES INC  ","invoice":"2020-07-31","gross":"2185.2400","status":"Paid","description":"Advertising","alt":"6343200"},{"0":"3625","name":"MID-ATLANTIC NEWSPAPER SERVICES INC  ","invoice":"2020-07-31","gross":"1329.3000","status":"Paid","description":"Advertising","alt":"6343200"}]