[{"0":"48459","name":"MID-ATLANTIC NEWSPAPER SERVICES INC ","invoice":"2026-06-03","gross":"2041.0800","status":"Paid","description":"Advertising","alt":"6343200"},{"0":"48571","name":"MID-ATLANTIC NEWSPAPER SERVICES INC ","invoice":"2026-06-03","gross":"1944.5900","status":"Paid","description":"Advertising","alt":"6343200"},{"0":"48460","name":"MID-ATLANTIC NEWSPAPER SERVICES INC ","invoice":"2026-06-03","gross":"3942.7200","status":"Paid","description":"Advertising","alt":"6343200"},{"0":"48461","name":"MID-ATLANTIC NEWSPAPER SERVICES INC ","invoice":"2026-06-03","gross":"2675.5800","status":"Paid","description":"Advertising","alt":"6343200"},{"0":"48462","name":"MID-ATLANTIC NEWSPAPER SERVICES INC ","invoice":"2026-06-08","gross":"889.3800","status":"Paid","description":"Advertising","alt":"6343200"},{"0":"48463","name":"MID-ATLANTIC NEWSPAPER SERVICES INC ","invoice":"2026-06-08","gross":"5686.2000","status":"Paid","description":"Advertising","alt":"6343200"},{"0":"48464","name":"MID-ATLANTIC NEWSPAPER SERVICES INC ","invoice":"2026-06-08","gross":"6525.1800","status":"Paid","description":"Advertising","alt":"6343200"},{"0":"48465","name":"MID-ATLANTIC NEWSPAPER SERVICES INC ","invoice":"2026-06-08","gross":"1036.4000","status":"Paid","description":"Advertising","alt":"6343200"},{"0":"48466","name":"MID-ATLANTIC NEWSPAPER SERVICES INC ","invoice":"2026-06-08","gross":"2774.8000","status":"Paid","description":"Advertising","alt":"6343200"},{"0":"48467","name":"MID-ATLANTIC NEWSPAPER SERVICES INC ","invoice":"2026-06-08","gross":"1708.6200","status":"Paid","description":"Advertising","alt":"6343200"},{"0":"48468","name":"MID-ATLANTIC NEWSPAPER SERVICES INC ","invoice":"2026-06-08","gross":"2420.1800","status":"Paid","description":"Advertising","alt":"6343200"},{"0":"48469","name":"MID-ATLANTIC NEWSPAPER SERVICES INC ","invoice":"2026-06-08","gross":"4742.8400","status":"Paid","description":"Advertising","alt":"6343200"},{"0":"48470","name":"MID-ATLANTIC NEWSPAPER SERVICES INC ","invoice":"2026-06-08","gross":"4901.6000","status":"Paid","description":"Advertising","alt":"6343200"},{"0":"48471","name":"MID-ATLANTIC NEWSPAPER SERVICES INC ","invoice":"2026-06-08","gross":"5495.4700","status":"Paid","description":"Advertising","alt":"6343200"},{"0":"48472","name":"MID-ATLANTIC NEWSPAPER SERVICES INC ","invoice":"2026-06-08","gross":"795.7000","status":"Paid","description":"Advertising","alt":"6343200"},{"0":"48473","name":"MID-ATLANTIC NEWSPAPER SERVICES INC ","invoice":"2026-06-08","gross":"552.1200","status":"Paid","description":"Advertising","alt":"6343200"},{"0":"48474","name":"MID-ATLANTIC NEWSPAPER SERVICES INC ","invoice":"2026-06-08","gross":"4636.8700","status":"Paid","description":"Advertising","alt":"6343200"},{"0":"48475","name":"MID-ATLANTIC NEWSPAPER SERVICES INC ","invoice":"2026-06-09","gross":"1830.0400","status":"Paid","description":"Advertising","alt":"6343200"},{"0":"48476","name":"MID-ATLANTIC NEWSPAPER SERVICES INC ","invoice":"2026-06-09","gross":"1246.9700","status":"Paid","description":"Advertising","alt":"6343200"},{"0":"48477","name":"MID-ATLANTIC NEWSPAPER SERVICES INC ","invoice":"2026-06-09","gross":"1239.7800","status":"Paid","description":"Advertising","alt":"6343200"},{"0":"48478","name":"MID-ATLANTIC NEWSPAPER SERVICES INC ","invoice":"2026-06-09","gross":"9943.1300","status":"Paid","description":"Advertising","alt":"6343200"},{"0":"48479","name":"MID-ATLANTIC NEWSPAPER SERVICES INC ","invoice":"2026-06-09","gross":"3120.6800","status":"Paid","description":"Advertising","alt":"6343200"},{"0":"48480","name":"MID-ATLANTIC NEWSPAPER SERVICES INC ","invoice":"2026-06-10","gross":"5221.2200","status":"Paid","description":"Advertising","alt":"6343200"},{"0":"48481","name":"MID-ATLANTIC NEWSPAPER SERVICES INC ","invoice":"2026-06-10","gross":"1666.9800","status":"Paid","description":"Advertising","alt":"6343200"},{"0":"48482","name":"MID-ATLANTIC NEWSPAPER SERVICES INC ","invoice":"2026-06-10","gross":"15536.4900","status":"Paid","description":"Advertising","alt":"6343200"},{"0":"48483","name":"MID-ATLANTIC NEWSPAPER SERVICES INC ","invoice":"2026-06-11","gross":"788.4600","status":"Paid","description":"Advertising","alt":"6343200"},{"0":"48572","name":"MID-ATLANTIC NEWSPAPER SERVICES INC ","invoice":"2026-06-11","gross":"907.2000","status":"Paid","description":"Advertising","alt":"6343200"},{"0":"48573","name":"MID-ATLANTIC NEWSPAPER SERVICES INC ","invoice":"2026-06-11","gross":"734.5400","status":"Paid","description":"Advertising","alt":"6343200"},{"0":"48574","name":"MID-ATLANTIC NEWSPAPER SERVICES INC ","invoice":"2026-06-11","gross":"28148.4500","status":"Paid","description":"Advertising","alt":"6343200"},{"0":"48575","name":"MID-ATLANTIC NEWSPAPER SERVICES INC ","invoice":"2026-06-12","gross":"3369.4300","status":"Paid","description":"Advertising","alt":"6343200"},{"0":"48576","name":"MID-ATLANTIC NEWSPAPER SERVICES INC ","invoice":"2026-06-12","gross":"665.0000","status":"Paid","description":"Advertising","alt":"6343200"},{"0":"48577","name":"MID-ATLANTIC NEWSPAPER SERVICES INC ","invoice":"2026-06-16","gross":"3854.1200","status":"Paid","description":"Advertising","alt":"6343200"},{"0":"48578","name":"MID-ATLANTIC NEWSPAPER SERVICES INC ","invoice":"2026-06-16","gross":"33084.4500","status":"Paid","description":"Advertising","alt":"6343200"},{"0":"48579","name":"MID-ATLANTIC NEWSPAPER SERVICES INC ","invoice":"2026-06-16","gross":"1074.9700","status":"Paid","description":"Advertising","alt":"6343200"},{"0":"48580","name":"MID-ATLANTIC NEWSPAPER SERVICES INC ","invoice":"2026-06-16","gross":"1074.9700","status":"Paid","description":"Advertising","alt":"6343200"},{"0":"48581","name":"MID-ATLANTIC NEWSPAPER SERVICES INC ","invoice":"2026-06-16","gross":"2080.5000","status":"Paid","description":"Advertising","alt":"6343200"},{"0":"48582","name":"MID-ATLANTIC NEWSPAPER SERVICES INC ","invoice":"2026-06-16","gross":"2080.5000","status":"Paid","description":"Advertising","alt":"6343200"},{"0":"48583","name":"MID-ATLANTIC NEWSPAPER SERVICES INC ","invoice":"2026-06-16","gross":"13718.0300","status":"Paid","description":"Advertising","alt":"6343200"},{"0":"48584","name":"MID-ATLANTIC NEWSPAPER SERVICES INC ","invoice":"2026-06-17","gross":"528.8000","status":"Paid","description":"Advertising","alt":"6343200"},{"0":"48585","name":"MID-ATLANTIC NEWSPAPER SERVICES INC ","invoice":"2026-06-17","gross":"1872.7200","status":"Paid","description":"Advertising","alt":"6343200"},{"0":"48586","name":"MID-ATLANTIC NEWSPAPER SERVICES INC ","invoice":"2026-06-17","gross":"3219.3600","status":"Paid","description":"Advertising","alt":"6343200"},{"0":"48587","name":"MID-ATLANTIC NEWSPAPER SERVICES INC ","invoice":"2026-06-17","gross":"1554.7000","status":"Paid","description":"Advertising","alt":"6343200"},{"0":"48588","name":"MID-ATLANTIC NEWSPAPER SERVICES INC ","invoice":"2026-06-17","gross":"294.3800","status":"Paid","description":"Advertising","alt":"6343200"},{"0":"48589","name":"MID-ATLANTIC NEWSPAPER SERVICES INC ","invoice":"2026-06-17","gross":"1499.6300","status":"Paid","description":"Advertising","alt":"6343200"}]