[{"0":"26191","name":"ACH PAYEE  ","invoice":"2023-06-02","gross":"1504.0100","status":"Paid","description":"Grants & Payments to","alt":"6602000"},{"0":"26192","name":"ACH PAYEE  ","invoice":"2023-06-02","gross":"1504.0100","status":"Paid","description":"Grants & Payments to","alt":"6602000"},{"0":"26193","name":"ACH PAYEE  ","invoice":"2023-06-02","gross":"5185.9200","status":"Paid","description":"Grants & Payments to","alt":"6602000"},{"0":"26194","name":"ACH PAYEE  ","invoice":"2023-06-02","gross":"2936.6200","status":"Paid","description":"Grants & Payments to","alt":"6602000"},{"0":"26195","name":"ACH PAYEE  ","invoice":"2023-06-02","gross":"1915.2400","status":"Paid","description":"Grants & Payments to","alt":"6602000"},{"0":"26196","name":"ACH PAYEE  ","invoice":"2023-06-02","gross":"3172.2600","status":"Paid","description":"Grants & Payments to","alt":"6602000"},{"0":"26197","name":"ACH PAYEE  ","invoice":"2023-06-02","gross":"1855.5500","status":"Paid","description":"Grants & Payments to","alt":"6602000"},{"0":"26198","name":"ACH PAYEE  ","invoice":"2023-06-02","gross":"2299.0300","status":"Paid","description":"Grants & Payments to","alt":"6602000"},{"0":"26200","name":"ACH PAYEE  ","invoice":"2023-06-02","gross":"2135.0300","status":"Paid","description":"Grants & Payments to","alt":"6602000"},{"0":"26201","name":"ACH PAYEE  ","invoice":"2023-06-02","gross":"2080.7400","status":"Paid","description":"Grants & Payments to","alt":"6602000"},{"0":"26202","name":"ACH PAYEE  ","invoice":"2023-06-02","gross":"344.0500","status":"Paid","description":"Grants & Payments to","alt":"6602000"},{"0":"26203","name":"ACH PAYEE  ","invoice":"2023-06-02","gross":"839.6700","status":"Paid","description":"Grants & Payments to","alt":"6602000"},{"0":"26205","name":"ACH PAYEE  ","invoice":"2023-06-02","gross":"8307.0600","status":"Paid","description":"Grants & Payments to","alt":"6602000"},{"0":"26207","name":"ACH PAYEE  ","invoice":"2023-06-02","gross":"2238.1400","status":"Paid","description":"Grants & Payments to","alt":"6602000"},{"0":"26208","name":"ACH PAYEE  ","invoice":"2023-06-02","gross":"8043.3800","status":"Paid","description":"Grants & Payments to","alt":"6602000"},{"0":"26210","name":"ACH PAYEE  ","invoice":"2023-06-02","gross":"2090.9500","status":"Paid","description":"Grants & Payments to","alt":"6602000"},{"0":"26211","name":"ACH PAYEE  ","invoice":"2023-06-02","gross":"3425.8700","status":"Paid","description":"Grants & Payments to","alt":"6602000"},{"0":"26387","name":"ACH PAYEE  ","invoice":"2023-06-27","gross":"40596.1700","status":"Paid","description":"Grants & Payments to","alt":"6602000"},{"0":"26023","name":"ALEPPO TOWNSHIP  ","invoice":"2023-06-01","gross":"5782.4800","status":"Paid","description":"Grants & Payments to","alt":"6602000"},{"0":"26036","name":"ALLEGHENY COUNTY COMMISSIONERS  ","invoice":"2023-06-01","gross":"8056403.5800","status":"Paid","description":"Grants & Payments to","alt":"6602000"},{"0":"26037","name":"ALLEGHENY REGIONAL ASSET DISTRICT  ","invoice":"2023-06-01","gross":"14996140.4900","status":"Paid","description":"Grants & Payments to","alt":"6602000"},{"0":"26039","name":"ALLEGHENY REGIONAL ASSET DISTRICT  ","invoice":"2023-06-01","gross":"1116666.6700","status":"Paid","description":"Grants & Payments to","alt":"6602000"},{"0":"25916","name":"ASPINWALL BOROUGH  ","invoice":"2023-06-01","gross":"14442.0100","status":"Paid","description":"Grants & Payments to","alt":"6602000"},{"0":"25917","name":"AVALON BOROUGH  ","invoice":"2023-06-01","gross":"36678.8700","status":"Paid","description":"Grants & Payments to","alt":"6602000"},{"0":"25918","name":"BALDWIN BOROUGH  ","invoice":"2023-06-01","gross":"114230.7800","status":"Paid","description":"Grants & Payments to","alt":"6602000"},{"0":"25971","name":"BALDWIN TOWNSHIP  ","invoice":"2023-06-01","gross":"11368.1800","status":"Paid","description":"Grants & Payments to","alt":"6602000"},{"0":"25999","name":"BELL ACRES BOROUGH  ","invoice":"2023-06-01","gross":"5842.4400","status":"Paid","description":"Grants & Payments to","alt":"6602000"},{"0":"25920","name":"BEN AVON BOROUGH  ","invoice":"2023-06-01","gross":"7792.6400","status":"Paid","description":"Grants & Payments to","alt":"6602000"},{"0":"25921","name":"BEN AVON HEIGHTS BOROUGH  ","invoice":"2023-06-01","gross":"2117.0800","status":"Paid","description":"Grants & Payments to","alt":"6602000"},{"0":"25922","name":"BETHEL PARK BOROUGH  ","invoice":"2023-06-01","gross":"129376.0500","status":"Paid","description":"Grants & Payments to","alt":"6602000"},{"0":"26000","name":"BLAWNOX BOROUGH  ","invoice":"2023-06-01","gross":"8949.1400","status":"Paid","description":"Grants & Payments to","alt":"6602000"},{"0":"25930","name":"BOROUGH OF CHURCHILL  ","invoice":"2023-06-01","gross":"16936.9100","status":"Paid","description":"Grants & Payments to","alt":"6602000"},{"0":"25923","name":"BRACKENRIDGE BOROUGH  ","invoice":"2023-06-01","gross":"18616.9300","status":"Paid","description":"Grants & Payments to","alt":"6602000"},{"0":"25924","name":"BRADDOCK BOROUGH  ","invoice":"2023-06-01","gross":"21442.2800","status":"Paid","description":"Grants & Payments to","alt":"6602000"},{"0":"25925","name":"BRADDOCK HILLS BOROUGH  ","invoice":"2023-06-01","gross":"13538.1200","status":"Paid","description":"Grants & Payments to","alt":"6602000"},{"0":"26001","name":"BRADFORD WOODS BOROUGH  ","invoice":"2023-06-01","gross":"3446.1700","status":"Paid","description":"Grants & Payments to","alt":"6602000"},{"0":"26002","name":"BRENTWOOD BOROUGH  ","invoice":"2023-06-01","gross":"76022.7600","status":"Paid","description":"Grants & Payments to","alt":"6602000"},{"0":"25926","name":"BRIDGEVILLE BOROUGH  ","invoice":"2023-06-01","gross":"27337.9600","status":"Paid","description":"Grants & Payments to","alt":"6602000"},{"0":"25927","name":"CARNEGIE BOROUGH  ","invoice":"2023-06-01","gross":"47002.5600","status":"Paid","description":"Grants & Payments to","alt":"6602000"},{"0":"25928","name":"CASTLE SHANNON BOROUGH  ","invoice":"2023-06-01","gross":"55845.5200","status":"Paid","description":"Grants & Payments to","alt":"6602000"},{"0":"25929","name":"CHALFONT BOROUGH  ","invoice":"2023-06-01","gross":"5326.2600","status":"Paid","description":"Grants & Payments to","alt":"6602000"},{"0":"26003","name":"CHESWICK BOROUGH  ","invoice":"2023-06-01","gross":"7760.4600","status":"Paid","description":"Grants & Payments to","alt":"6602000"},{"0":"26190","name":"CHK PAYEE  ","invoice":"2023-06-02","gross":"1438.9200","status":"Paid","description":"Grants & Payments to","alt":"6602000"},{"0":"26199","name":"CHK PAYEE  ","invoice":"2023-06-02","gross":"835.0000","status":"Paid","description":"Grants & Payments to","alt":"6602000"},{"0":"26204","name":"CHK PAYEE  ","invoice":"2023-06-02","gross":"3735.5500","status":"Paid","description":"Grants & Payments to","alt":"6602000"},{"0":"26206","name":"CHK PAYEE  ","invoice":"2023-06-02","gross":"3332.6800","status":"Paid","description":"Grants & Payments to","alt":"6602000"},{"0":"26209","name":"CHK PAYEE  ","invoice":"2023-06-02","gross":"6177.4500","status":"Paid","description":"Grants & Payments to","alt":"6602000"},{"0":"26212","name":"CHK PAYEE  ","invoice":"2023-06-02","gross":"2724.2800","status":"Paid","description":"Grants & Payments to","alt":"6602000"},{"0":"26213","name":"CHK PAYEE  ","invoice":"2023-06-02","gross":"3673.1300","status":"Paid","description":"Grants & Payments to","alt":"6602000"},{"0":"26214","name":"CHK PAYEE  ","invoice":"2023-06-02","gross":"124.6200","status":"Paid","description":"Grants & Payments to","alt":"6602000"},{"0":"26041","name":"CITY OF CLAIRTON  ","invoice":"2023-06-01","gross":"65255.5200","status":"Paid","description":"Grants & Payments to","alt":"6602000"},{"0":"25914","name":"CITY OF DUQUESNE  ","invoice":"2023-06-01","gross":"84310.5300","status":"Paid","description":"Grants & Payments to","alt":"6602000"},{"0":"25915","name":"CITY OF MCKEESPORT  ","invoice":"2023-06-01","gross":"234197.9500","status":"Paid","description":"Grants & Payments to","alt":"6602000"},{"0":"26044","name":"CITY OF PHILADELPHIA CITIES OF THE FIRST CLASS","invoice":"2023-06-01","gross":"45089651.3300","status":"Paid","description":"Grants & Payments to","alt":"6602000"},{"0":"26035","name":"CITY OF PITTSBURGH  ","invoice":"2023-06-01","gross":"3176411.0400","status":"Paid","description":"Grants & Payments to","alt":"6602000"},{"0":"26024","name":"COLLIER TOWNSHIP  ","invoice":"2023-06-01","gross":"32540.8400","status":"Paid","description":"Grants & Payments to","alt":"6602000"},{"0":"26004","name":"CORAOPOLIS BOROUGH  ","invoice":"2023-06-01","gross":"47311.3400","status":"Paid","description":"Grants & Payments to","alt":"6602000"},{"0":"25931","name":"CRAFTON BOROUGH  ","invoice":"2023-06-01","gross":"37629.1500","status":"Paid","description":"Grants & Payments to","alt":"6602000"},{"0":"26025","name":"CRESCENT TOWNSHIP  ","invoice":"2023-06-01","gross":"10235.0800","status":"Paid","description":"Grants & Payments to","alt":"6602000"},{"0":"26005","name":"DORMONT BOROUGH  ","invoice":"2023-06-01","gross":"60318.4200","status":"Paid","description":"Grants & Payments to","alt":"6602000"},{"0":"25932","name":"DRAVOSBURG BOROUGH  ","invoice":"2023-06-01","gross":"11728.3300","status":"Paid","description":"Grants & Payments to","alt":"6602000"},{"0":"26026","name":"EAST DEER TOWNSHIP  ","invoice":"2023-06-01","gross":"6063.3600","status":"Paid","description":"Grants & Payments to","alt":"6602000"},{"0":"25933","name":"EAST MCKEESPORT BOROUGH  ","invoice":"2023-06-01","gross":"15730.1200","status":"Paid","description":"Grants & Payments to","alt":"6602000"},{"0":"25934","name":"EAST PITTSBURGH BOROUGH  ","invoice":"2023-06-01","gross":"22026.3900","status":"Paid","description":"Grants & Payments to","alt":"6602000"},{"0":"25935","name":"EDGEWOOD BOROUGH  ","invoice":"2023-06-01","gross":"17171.0000","status":"Paid","description":"Grants & Payments to","alt":"6602000"},{"0":"26006","name":"EDGEWORTH BOROUGH  ","invoice":"2023-06-01","gross":"5958.6900","status":"Paid","description":"Grants & Payments to","alt":"6602000"},{"0":"25936","name":"ELIZABETH BOROUGH  ","invoice":"2023-06-01","gross":"9287.7800","status":"Paid","description":"Grants & Payments to","alt":"6602000"},{"0":"26027","name":"ELIZABETH TOWNSHIP  ","invoice":"2023-06-01","gross":"46130.0200","status":"Paid","description":"Grants & Payments to","alt":"6602000"},{"0":"26007","name":"EMSWORTH BOROUGH  ","invoice":"2023-06-01","gross":"11248.8000","status":"Paid","description":"Grants & Payments to","alt":"6602000"},{"0":"25937","name":"ETNA BOROUGH  ","invoice":"2023-06-01","gross":"24077.2100","status":"Paid","description":"Grants & Payments to","alt":"6602000"},{"0":"25988","name":"FAWN TOWNSHIP  ","invoice":"2023-06-01","gross":"6497.3000","status":"Paid","description":"Grants & Payments to","alt":"6602000"},{"0":"25989","name":"FINDLAY TOWNSHIP  ","invoice":"2023-06-01","gross":"19261.8200","status":"Paid","description":"Grants & Payments to","alt":"6602000"},{"0":"25938","name":"FOREST HILLS BOROUGH  ","invoice":"2023-06-01","gross":"39269.2200","status":"Paid","description":"Grants & Payments to","alt":"6602000"},{"0":"26032","name":"FORWARD TOWNSHIP  ","invoice":"2023-06-01","gross":"7335.7400","status":"Paid","description":"Grants & Payments to","alt":"6602000"},{"0":"25939","name":"FOX CHAPEL BOROUGH  ","invoice":"2023-06-01","gross":"15737.9200","status":"Paid","description":"Grants & Payments to","alt":"6602000"},{"0":"26043","name":"FRANKLIN PARK BOROUGH  ","invoice":"2023-06-01","gross":"33492.9400","status":"Paid","description":"Grants & Payments to","alt":"6602000"},{"0":"25990","name":"FRAZER TOWNSHIP  ","invoice":"2023-06-01","gross":"1380.0800","status":"Paid","description":"Grants & Payments to","alt":"6602000"},{"0":"26042","name":"GLASSPORT BOROUGH  ","invoice":"2023-06-01","gross":"45839.0400","status":"Paid","description":"Grants & Payments to","alt":"6602000"},{"0":"25919","name":"GLENFIELD BOROUGH  ","invoice":"2023-06-01","gross":"685.7100","status":"Paid","description":"Grants & Payments to","alt":"6602000"},{"0":"25940","name":"GREEN TREE BOROUGH  ","invoice":"2023-06-01","gross":"24740.8400","status":"Paid","description":"Grants & Payments to","alt":"6602000"},{"0":"25991","name":"HAMPTON TOWNSHIP  ","invoice":"2023-06-01","gross":"56089.2400","status":"Paid","description":"Grants & Payments to","alt":"6602000"},{"0":"25992","name":"HARMAR TOWNSHIP  ","invoice":"2023-06-01","gross":"8601.1800","status":"Paid","description":"Grants & Payments to","alt":"6602000"},{"0":"25972","name":"HARRISON TOWNSHIP  ","invoice":"2023-06-01","gross":"44542.5600","status":"Paid","description":"Grants & Payments to","alt":"6602000"},{"0":"26008","name":"HAYSVILLE BOROUGH  ","invoice":"2023-06-01","gross":"331.6900","status":"Paid","description":"Grants & Payments to","alt":"6602000"},{"0":"26009","name":"HEIDELBERG BOROUGH  ","invoice":"2023-06-01","gross":"7295.1800","status":"Paid","description":"Grants & Payments to","alt":"6602000"},{"0":"25941","name":"HOMESTEAD BOROUGH  ","invoice":"2023-06-01","gross":"26083.1800","status":"Paid","description":"Grants & Payments to","alt":"6602000"},{"0":"25993","name":"INDIANA TOWNSHIP  ","invoice":"2023-06-01","gross":"22862.0100","status":"Paid","description":"Grants & Payments to","alt":"6602000"},{"0":"26010","name":"INGRAM BOROUGH  ","invoice":"2023-06-01","gross":"17499.2200","status":"Paid","description":"Grants & Payments to","alt":"6602000"},{"0":"26011","name":"JEFFERSON BOROUGH  ","invoice":"2023-06-01","gross":"55492.3200","status":"Paid","description":"Grants & Payments to","alt":"6602000"},{"0":"25973","name":"KENNEDY TOWNSHIP  ","invoice":"2023-06-01","gross":"26278.1600","status":"Paid","description":"Grants & Payments to","alt":"6602000"},{"0":"25994","name":"KILBUCK TOWNSHIP  ","invoice":"2023-06-01","gross":"2409.3000","status":"Paid","description":"Grants & Payments to","alt":"6602000"},{"0":"25974","name":"LEET TOWNSHIP  ","invoice":"2023-06-01","gross":"8811.6400","status":"Paid","description":"Grants & Payments to","alt":"6602000"},{"0":"25942","name":"LEETSDALE BOROUGH  ","invoice":"2023-06-01","gross":"9547.2300","status":"Paid","description":"Grants & Payments to","alt":"6602000"},{"0":"25943","name":"LIBERTY BOROUGH  ","invoice":"2023-06-01","gross":"14673.4400","status":"Paid","description":"Grants & Payments to","alt":"6602000"},{"0":"25944","name":"LINCOLN BOROUGH  ","invoice":"2023-06-01","gross":"5681.7200","status":"Paid","description":"Grants & Payments to","alt":"6602000"},{"0":"25995","name":"MARSHALL TOWNSHIP  ","invoice":"2023-06-01","gross":"22403.5500","status":"Paid","description":"Grants & Payments to","alt":"6602000"},{"0":"26028","name":"MCCANDLESS TOWNSHIP  ","invoice":"2023-06-01","gross":"73272.9200","status":"Paid","description":"Grants & Payments to","alt":"6602000"},{"0":"25945","name":"MCKEES ROCKS BOROUGH  ","invoice":"2023-06-01","gross":"55408.4500","status":"Paid","description":"Grants & Payments to","alt":"6602000"},{"0":"26012","name":"MILLVALE BOROUGH  ","invoice":"2023-06-01","gross":"24593.6300","status":"Paid","description":"Grants & Payments to","alt":"6602000"},{"0":"26013","name":"MONROEVILLE BOROUGH  ","invoice":"2023-06-01","gross":"177850.1800","status":"Paid","description":"Grants & Payments to","alt":"6602000"},{"0":"25996","name":"MOON TOWNSHIP  ","invoice":"2023-06-01","gross":"79573.0400","status":"Paid","description":"Grants & Payments to","alt":"6602000"},{"0":"25975","name":"MT LEBANON TOWNSHIP  ","invoice":"2023-06-01","gross":"173185.3500","status":"Paid","description":"Grants & Payments to","alt":"6602000"},{"0":"25946","name":"MT OLIVER BOROUGH  ","invoice":"2023-06-01","gross":"44220.2300","status":"Paid","description":"Grants & Payments to","alt":"6602000"},{"0":"26014","name":"MUNHALL BOROUGH  ","invoice":"2023-06-01","gross":"81966.0500","status":"Paid","description":"Grants & Payments to","alt":"6602000"},{"0":"25976","name":"NEVILLE TOWNSHIP  ","invoice":"2023-06-01","gross":"4334.9700","status":"Paid","description":"Grants & Payments to","alt":"6602000"},{"0":"26015","name":"NORTH BRADDOCK BOROUGH  ","invoice":"2023-06-01","gross":"37766.0700","status":"Paid","description":"Grants & Payments to","alt":"6602000"},{"0":"26033","name":"NORTH FAYETTE TOWNSHIP  ","invoice":"2023-06-01","gross":"52457.6500","status":"Paid","description":"Grants & Payments to","alt":"6602000"},{"0":"25977","name":"NORTH VERSAILLES TOWNSHIP  ","invoice":"2023-06-01","gross":"65973.1400","status":"Paid","description":"Grants & Payments to","alt":"6602000"},{"0":"25947","name":"OAKDALE BOROUGH  ","invoice":"2023-06-01","gross":"6297.2000","status":"Paid","description":"Grants & Payments to","alt":"6602000"},{"0":"25948","name":"OAKMONT BOROUGH THE BOROUGH OF OAKMONT","invoice":"2023-06-01","gross":"22384.5800","status":"Paid","description":"Grants & Payments to","alt":"6602000"},{"0":"25978","name":"OHARA TOWNSHIP  ","invoice":"2023-06-01","gross":"28262.1500","status":"Paid","description":"Grants & Payments to","alt":"6602000"},{"0":"26038","name":"OHIO TOWNSHIP  ","invoice":"2023-06-01","gross":"20726.0900","status":"Paid","description":"Grants & Payments to","alt":"6602000"},{"0":"26016","name":"OSBORNE BOROUGH  ","invoice":"2023-06-01","gross":"2138.3500","status":"Paid","description":"Grants & Payments to","alt":"6602000"},{"0":"25979","name":"PENN HILLS TOWNSHIP  ","invoice":"2023-06-01","gross":"334896.7500","status":"Paid","description":"Grants & Payments to","alt":"6602000"},{"0":"25949","name":"PENNSBURY VILLAGE BOROUGH  ","invoice":"2023-06-01","gross":"3229.1900","status":"Paid","description":"Grants & Payments to","alt":"6602000"},{"0":"26045","name":"Philadelphia School District  ","invoice":"2023-06-01","gross":"1594169.7900","status":"Paid","description":"Grants & Payments to","alt":"6602000"},{"0":"25997","name":"PINE TOWNSHIP  ","invoice":"2023-06-01","gross":"40530.1900","status":"Paid","description":"Grants & Payments to","alt":"6602000"},{"0":"25950","name":"PITCAIRN BOROUGH  ","invoice":"2023-06-01","gross":"24731.1900","status":"Paid","description":"Grants & Payments to","alt":"6602000"},{"0":"25951","name":"PLEASANT HILLS BOROUGH  ","invoice":"2023-06-01","gross":"43289.5200","status":"Paid","description":"Grants & Payments to","alt":"6602000"},{"0":"25952","name":"PLUM BOROUGH  ","invoice":"2023-06-01","gross":"108964.6300","status":"Paid","description":"Grants & Payments to","alt":"6602000"},{"0":"25953","name":"PORT VUE BOROUGH  ","invoice":"2023-06-01","gross":"26445.3800","status":"Paid","description":"Grants & Payments to","alt":"6602000"},{"0":"26017","name":"RANKIN BOROUGH  ","invoice":"2023-06-01","gross":"23878.6000","status":"Paid","description":"Grants & Payments to","alt":"6602000"},{"0":"25980","name":"RESERVE TOWNSHIP  ","invoice":"2023-06-01","gross":"14690.2800","status":"Paid","description":"Grants & Payments to","alt":"6602000"},{"0":"25998","name":"RICHLAND TOWNSHIP  ","invoice":"2023-06-01","gross":"29970.3000","status":"Paid","description":"Grants & Payments to","alt":"6602000"},{"0":"25981","name":"ROBINSON TOWNSHIP  ","invoice":"2023-06-01","gross":"48287.2600","status":"Paid","description":"Grants & Payments to","alt":"6602000"},{"0":"25982","name":"ROSS TOWNSHIP  ","invoice":"2023-06-01","gross":"98910.9000","status":"Paid","description":"Grants & Payments to","alt":"6602000"},{"0":"25954","name":"ROSSLYN FARMS BOROUGH  ","invoice":"2023-06-01","gross":"2396.3100","status":"Paid","description":"Grants & Payments to","alt":"6602000"},{"0":"26029","name":"SCOTT TOWNSHIP  ","invoice":"2023-06-01","gross":"83935.0200","status":"Paid","description":"Grants & Payments to","alt":"6602000"},{"0":"25955","name":"SEWICKLEY BOROUGH  ","invoice":"2023-06-01","gross":"18668.7300","status":"Paid","description":"Grants & Payments to","alt":"6602000"},{"0":"25956","name":"SEWICKLEY HEIGHTS BOROUGH  ","invoice":"2023-06-01","gross":"3798.6000","status":"Paid","description":"Grants & Payments to","alt":"6602000"},{"0":"25957","name":"SEWICKLEY HILLS BOROUGH  ","invoice":"2023-06-01","gross":"2012.2400","status":"Paid","description":"Grants & Payments to","alt":"6602000"},{"0":"25983","name":"SHALER TOWNSHIP  ","invoice":"2023-06-01","gross":"87576.1000","status":"Paid","description":"Grants & Payments to","alt":"6602000"},{"0":"25958","name":"SHARPSBURG BOROUGH  ","invoice":"2023-06-01","gross":"23814.4800","status":"Paid","description":"Grants & Payments to","alt":"6602000"},{"0":"25984","name":"SOUTH FAYETTE TOWNSHIP  ","invoice":"2023-06-01","gross":"74369.9400","status":"Paid","description":"Grants & Payments to","alt":"6602000"},{"0":"26034","name":"SOUTH PARK TOWNSHIP  ","invoice":"2023-06-01","gross":"47875.6200","status":"Paid","description":"Grants & Payments to","alt":"6602000"},{"0":"25985","name":"SOUTH VERSAILLES TOWNSHIP  ","invoice":"2023-06-01","gross":"1014.4900","status":"Paid","description":"Grants & Payments to","alt":"6602000"},{"0":"25959","name":"SPRINGDALE BOROUGH  ","invoice":"2023-06-01","gross":"22193.0300","status":"Paid","description":"Grants & Payments to","alt":"6602000"},{"0":"26030","name":"SPRINGDALE TOWNSHIP TOWNSHIP OF SPRINGDALE TREAS","invoice":"2023-06-01","gross":"6958.7900","status":"Paid","description":"Grants & Payments to","alt":"6602000"},{"0":"25986","name":"STOWE TOWNSHIP  ","invoice":"2023-06-01","gross":"50114.6100","status":"Paid","description":"Grants & Payments to","alt":"6602000"},{"0":"25960","name":"SWISSVALE BOROUGH  ","invoice":"2023-06-01","gross":"57891.0400","status":"Paid","description":"Grants & Payments to","alt":"6602000"},{"0":"25961","name":"TARENTUM BOROUGH  ","invoice":"2023-06-01","gross":"24476.7100","status":"Paid","description":"Grants & Payments to","alt":"6602000"},{"0":"26018","name":"THORNBURG BOROUGH  ","invoice":"2023-06-01","gross":"2125.8600","status":"Paid","description":"Grants & Payments to","alt":"6602000"},{"0":"25962","name":"TURTLE CREEK BOROUGH  ","invoice":"2023-06-01","gross":"43260.3300","status":"Paid","description":"Grants & Payments to","alt":"6602000"},{"0":"26031","name":"UPPER ST CLAIR TOWNSHIP  ","invoice":"2023-06-01","gross":"96217.9600","status":"Paid","description":"Grants & Payments to","alt":"6602000"},{"0":"25963","name":"VERONA BOROUGH  ","invoice":"2023-06-01","gross":"15156.2900","status":"Paid","description":"Grants & Payments to","alt":"6602000"},{"0":"26019","name":"VERSAILLES BOROUGH  ","invoice":"2023-06-01","gross":"10319.5600","status":"Paid","description":"Grants & Payments to","alt":"6602000"},{"0":"25964","name":"WALL BOROUGH  ","invoice":"2023-06-01","gross":"3973.3200","status":"Paid","description":"Grants & Payments to","alt":"6602000"},{"0":"26040","name":"WEST DEER TOWNSHIP  ","invoice":"2023-06-01","gross":"36814.3700","status":"Paid","description":"Grants & Payments to","alt":"6602000"},{"0":"25965","name":"WEST ELIZABETH BOROUGH  ","invoice":"2023-06-01","gross":"1706.8100","status":"Paid","description":"Grants & Payments to","alt":"6602000"},{"0":"26020","name":"WEST HOMESTEAD BOROUGH  ","invoice":"2023-06-01","gross":"12252.7800","status":"Paid","description":"Grants & Payments to","alt":"6602000"},{"0":"25966","name":"WEST MIFFLIN BOROUGH  ","invoice":"2023-06-01","gross":"144486.0600","status":"Paid","description":"Grants & Payments to","alt":"6602000"},{"0":"26021","name":"WEST VIEW BOROUGH  ","invoice":"2023-06-01","gross":"34912.2600","status":"Paid","description":"Grants & Payments to","alt":"6602000"},{"0":"25967","name":"WHITAKER BOROUGH  ","invoice":"2023-06-01","gross":"11018.4300","status":"Paid","description":"Grants & Payments to","alt":"6602000"},{"0":"26022","name":"WHITE OAK BOROUGH  ","invoice":"2023-06-01","gross":"41041.5700","status":"Paid","description":"Grants & Payments to","alt":"6602000"},{"0":"25968","name":"WHITEHALL BOROUGH  ","invoice":"2023-06-01","gross":"81125.9000","status":"Paid","description":"Grants & Payments to","alt":"6602000"},{"0":"25987","name":"WILKINS TOWNSHIP  ","invoice":"2023-06-01","gross":"36641.7000","status":"Paid","description":"Grants & Payments to","alt":"6602000"},{"0":"25969","name":"WILKINSBURG BOROUGH  ","invoice":"2023-06-01","gross":"142391.6600","status":"Paid","description":"Grants & Payments to","alt":"6602000"},{"0":"25970","name":"WILMERDING BOROUGH  ","invoice":"2023-06-01","gross":"17299.3700","status":"Paid","description":"Grants & Payments to","alt":"6602000"}]