[{"0":"45740","name":"LEVEL 3 COMMUNICATIONS LLC ","invoice":"2025-10-01","gross":"3927.1700","status":"Paid","description":"Telecommunications Recurring F","alt":"6331110"},{"0":"45741","name":"LEVEL 3 COMMUNICATIONS LLC ","invoice":"2025-10-01","gross":"3242.0000","status":"Paid","description":"Telecommunications Recurring F","alt":"6331110"},{"0":"46323","name":"VERIZON BUSINESS ","invoice":"2025-10-20","gross":"1589.2500","status":"Paid","description":"Telecommunications Recurring F","alt":"6331110"},{"0":"46343","name":"VERIZON BUSINESS ","invoice":"2025-10-20","gross":"1426.5000","status":"Paid","description":"Telecommunications Recurring F","alt":"6331110"},{"0":"47062","name":"VERIZON BUSINESS ","invoice":"2025-10-20","gross":"181.4400","status":"Paid","description":"Telecommunications Recurring F","alt":"6331110"},{"0":"45806","name":"VERIZON BUSINESS ","invoice":"2025-10-08","gross":"3334.4500","status":"Paid","description":"Telecommunications Recurring F","alt":"6331110"}]