[{"0":"40842","name":"CAPITOL SUPPORT SERVICE  ","invoice":"2024-08-01","gross":"169.0500","status":"Paid","description":"Printing","alt":"6391030"},{"0":"40843","name":"CAPITOL SUPPORT SERVICE  ","invoice":"2024-08-07","gross":"66.2500","status":"Paid","description":"Printing","alt":"6391030"},{"0":"40844","name":"CAPITOL SUPPORT SERVICE  ","invoice":"2024-08-16","gross":"180.0000","status":"Paid","description":"Printing","alt":"6391030"},{"0":"40845","name":"CAPITOL SUPPORT SERVICE  ","invoice":"2024-08-16","gross":"272.8500","status":"Paid","description":"Printing","alt":"6391030"}]