[{"0":"43408","name":"ACCESS IT GROUP INC  ","invoice":"2025-03-19","gross":"5600.0000","status":"Paid","description":"Sftwre Lic Proc Rec","alt":"6371011"},{"0":"43574","name":"ACCESS IT GROUP INC  ","invoice":"2025-03-26","gross":"23976.0000","status":"Paid","description":"Sftwre Lic Proc Rec","alt":"6371011"},{"0":"43402","name":"BCC SOFTWARE  ","invoice":"2025-03-25","gross":"3779.0000","status":"Paid","description":"Sftwre Lic Proc Rec","alt":"6371011"},{"0":"43581","name":"BELL & HOWELL LLC BOWE BELL & HOWELL","invoice":"2025-03-31","gross":"4082.8400","status":"Paid","description":"Sftwre Lic Proc Rec","alt":"6371011"},{"0":"43579","name":"CDW-G  ","invoice":"2025-03-31","gross":"302.4100","status":"Paid","description":"Sftwre Lic Proc Rec","alt":"6371011"},{"0":"43407","name":"CDW-G  ","invoice":"2025-03-27","gross":"12060.0000","status":"Paid","description":"Sftwre Lic Proc Rec","alt":"6371011"},{"0":"43605","name":"CDW-G  ","invoice":"2025-03-28","gross":"55697.3400","status":"Paid","description":"Sftwre Lic Proc Rec","alt":"6371011"},{"0":"43344","name":"Insight Public Sector  ","invoice":"2025-03-14","gross":"261.9600","status":"Paid","description":"Sftwre Lic Proc Rec","alt":"6371011"},{"0":"43586","name":"Insight Public Sector  ","invoice":"2025-03-27","gross":"87.3200","status":"Paid","description":"Sftwre Lic Proc Rec","alt":"6371011"}]