[{"0":"23739","name":"RELX INC DBA LEXISNEXIS  ","invoice":"2022-08-31","gross":"550.0000","status":"Paid","description":"Prof Svcs-Not Spec'd","alt":"6343118"},{"0":"23150","name":"RELX INC DBA LEXISNEXIS  ","invoice":"2022-08-31","gross":"976.0600","status":"Paid","description":"Prof Svcs-Not Spec'd","alt":"6343118"},{"0":"23070","name":"RELX INC DBA LEXISNEXIS  ","invoice":"2022-08-31","gross":"130.0000","status":"Paid","description":"Subscriptions","alt":"6391040"},{"0":"23069","name":"RELX INC DBA LEXISNEXIS  ","invoice":"2022-08-31","gross":"480.0000","status":"Paid","description":"Legal Services/Fees","alt":"6342100"},{"0":"22998","name":"RELX INC DBA LEXISNEXIS  ","invoice":"2022-08-31","gross":"750.0000","status":"Paid","description":"Subscriptions","alt":"6391040"},{"0":"23205","name":"RELX INC DBA LEXISNEXIS  ","invoice":"2022-08-31","gross":"2922.0000","status":"Paid","description":"Prof Svcs-Not Spec'd","alt":"6343118"}]