[{"0":"47443","name":"VERIZON BUSINESS ","invoice":"2026-03-20","gross":"1589.2500","status":"Paid","description":"Telecommunications Recurring F","alt":"6331110"},{"0":"47444","name":"VERIZON BUSINESS ","invoice":"2026-03-20","gross":"1426.5000","status":"Paid","description":"Telecommunications Recurring F","alt":"6331110"},{"0":"47453","name":"VERIZON BUSINESS ","invoice":"2026-03-20","gross":"181.4700","status":"Paid","description":"Telecommunications Recurring F","alt":"6331110"},{"0":"47445","name":"VERIZON BUSINESS ","invoice":"2026-03-20","gross":"3963.6100","status":"Paid","description":"Toll free Telephone Services","alt":"6331160"},{"0":"47368","name":"VERIZON BUSINESS ","invoice":"2026-03-08","gross":"3321.0400","status":"Paid","description":"Telecommunications Recurring F","alt":"6331110"}]