[{"0":"47030","name":"ECKERT SEAMANS CHERIN AND MELLOTT LLC ","invoice":"2025-11-06","gross":"18398.0000","status":"Paid","description":"Legal Services/Fees","alt":"6342100"},{"0":"45953","name":"HANGLEY ARONCHICK SEGAL PUDLIN&SCHILLER ","invoice":"2025-11-04","gross":"654.5000","status":"Paid","description":"Legal Services/Fees","alt":"6342100"},{"0":"46335","name":"LAMB MCERLANE PC ","invoice":"2025-11-05","gross":"4867.5000","status":"Paid","description":"Legal Services/Fees","alt":"6342100"},{"0":"46653","name":"THOMSON REUTERS WEST PUBLISHING CORP WEST GROUP PAYMENT CENTER","invoice":"2025-11-01","gross":"432.4300","status":"Paid","description":"Legal Services/Fees","alt":"6342100"},{"0":"46654","name":"THOMSON REUTERS WEST PUBLISHING CORP WEST GROUP PAYMENT CENTER","invoice":"2025-11-01","gross":"2774.0300","status":"Paid","description":"Legal Services/Fees","alt":"6342100"}]