[{"0":"43642","name":"BNY MELLON  ","invoice":"2025-01-15","gross":"213.0600","status":"Paid","description":"Bank Service Charges","alt":"6343111"},{"0":"42951","name":"BNY MELLON  ","invoice":"2025-01-14","gross":"1652.3000","status":"Paid","description":"Bank Service Charges","alt":"6343111"},{"0":"42952","name":"BNY MELLON  ","invoice":"2025-01-14","gross":"12392.2400","status":"Paid","description":"Bank Service Charges","alt":"6343111"},{"0":"42953","name":"BNY MELLON  ","invoice":"2025-01-14","gross":"826.1500","status":"Paid","description":"Bank Service Charges","alt":"6343111"},{"0":"43034","name":"BNY MELLON  ","invoice":"2025-01-30","gross":"3471.3900","status":"Paid","description":"Bank Service Charges","alt":"6343111"},{"0":"43032","name":"BNY MELLON  ","invoice":"2025-01-14","gross":"7696.2100","status":"Paid","description":"Bank Service Charges","alt":"6343111"}]