[{"0":"3017","name":"OST INC  ","invoice":"2020-06-15","gross":"19493.7600","status":"Paid","description":"ITConsulting-General","alt":"6341218"},{"0":"3016","name":"OST INC  ","invoice":"2020-06-15","gross":"297.4400","status":"Paid","description":"ITConsulting-General","alt":"6341218"},{"0":"3015","name":"OST INC  ","invoice":"2020-06-15","gross":"18291.0000","status":"Paid","description":"ITConsulting-General","alt":"6341218"},{"0":"3014","name":"OST INC  ","invoice":"2020-06-15","gross":"5318.0400","status":"Paid","description":"ITConsulting-General","alt":"6341218"}]