[{"0":"18961","name":"BELL & HOWELL LLC BOWE BELL & HOWELL","invoice":"2021-09-30","gross":"1254.0800","status":"Paid","description":"Contracted Maintenance - Offic","alt":"6344420"},{"0":"18960","name":"BELL & HOWELL LLC BOWE BELL & HOWELL","invoice":"2021-09-30","gross":"3533.9800","status":"Paid","description":"Contracted Maintenance - Offic","alt":"6344420"},{"0":"18699","name":"XEROX CORPORATION  ","invoice":"2021-09-15","gross":"1514.0000","status":"Paid","description":"Contracted Maintenance - Offic","alt":"6344420"},{"0":"20030","name":"XEROX CORPORATION  ","invoice":"2021-09-01","gross":"1215.1000","status":"Paid","description":"Contracted Maintenance - Offic","alt":"6344420"},{"0":"18700","name":"XEROX CORPORATION  ","invoice":"2021-09-15","gross":"50.0000","status":"Paid","description":"Contracted Maintenance - Offic","alt":"6344420"},{"0":"20029","name":"XEROX CORPORATION  ","invoice":"2021-09-01","gross":"1230.9500","status":"Paid","description":"Contracted Maintenance - Offic","alt":"6344420"},{"0":"18701","name":"XEROX CORPORATION  ","invoice":"2021-09-15","gross":"206.1900","status":"Paid","description":"Contracted Maintenance - Offic","alt":"6344420"},{"0":"18702","name":"XEROX CORPORATION  ","invoice":"2021-09-15","gross":"50.0000","status":"Paid","description":"Contracted Maintenance - Offic","alt":"6344420"}]