[{"0":"3731","name":"BNY MELLON  ","invoice":"2020-03-11","gross":"1137.9800","status":"Paid","description":"Bank Service Charges","alt":"6343111"},{"0":"3732","name":"BNY MELLON  ","invoice":"2020-03-11","gross":"2757.8600","status":"Paid","description":"Bank Service Charges","alt":"6343111"},{"0":"3733","name":"BNY MELLON  ","invoice":"2020-03-11","gross":"502.8200","status":"Paid","description":"Bank Service Charges","alt":"6343111"},{"0":"3734","name":"BNY MELLON  ","invoice":"2020-03-11","gross":"1612.8000","status":"Paid","description":"Bank Service Charges","alt":"6343111"},{"0":"3753","name":"BNY MELLON  ","invoice":"2020-03-23","gross":"858.1100","status":"Paid","description":"Bank Service Charges","alt":"6343111"},{"0":"3754","name":"BNY MELLON  ","invoice":"2020-03-23","gross":"610.7900","status":"Paid","description":"Bank Service Charges","alt":"6343111"},{"0":"3755","name":"BNY MELLON  ","invoice":"2020-03-23","gross":"191.4400","status":"Paid","description":"Bank Service Charges","alt":"6343111"},{"0":"3726","name":"BNY MELLON  ","invoice":"2020-03-23","gross":"1370.0600","status":"Paid","description":"Bank Service Charges","alt":"6343111"},{"0":"3725","name":"BNY MELLON  ","invoice":"2020-03-23","gross":"6165.2500","status":"Paid","description":"Bank Service Charges","alt":"6343111"},{"0":"3723","name":"BNY MELLON  ","invoice":"2020-03-23","gross":"685.0300","status":"Paid","description":"Bank Service Charges","alt":"6343111"},{"0":"2274","name":"NOTTINGHAM  ","invoice":"2020-03-31","gross":"36935.3200","status":"Paid","description":"Bank Service Charges","alt":"6343111"},{"0":"2098","name":"PNC BANK  ","invoice":"2020-03-12","gross":"6785.0400","status":"Paid","description":"Bank Service Charges","alt":"6343111"},{"0":"2099","name":"PNC BANK  ","invoice":"2020-03-12","gross":"8778.4100","status":"Paid","description":"Bank Service Charges","alt":"6343111"},{"0":"2100","name":"PNC BANK  ","invoice":"2020-03-12","gross":"1343.6400","status":"Paid","description":"Bank Service Charges","alt":"6343111"},{"0":"2410","name":"WELLS FARGO BANKS  ","invoice":"2020-03-10","gross":"3486.9700","status":"Paid","description":"Bank Service Charges","alt":"6343111"},{"0":"2397","name":"WELLS FARGO BANKS  ","invoice":"2020-03-10","gross":"2320.8400","status":"Paid","description":"Bank Service Charges","alt":"6343111"},{"0":"2396","name":"WELLS FARGO BANKS  ","invoice":"2020-03-10","gross":"691.2200","status":"Paid","description":"Bank Service Charges","alt":"6343111"}]