[{"0":"48189","name":"AKF CONSULTINGGROUP AKF CONSULTING GROUP","invoice":"2026-05-17","gross":"8047.5000","status":"Paid","description":"Prof Svcs-Not Spec'd","alt":"6343118"},{"0":"48188","name":"ASCENSUS COLLEGE SAVINGS ","invoice":"2026-05-13","gross":"281006.5600","status":"Paid","description":"Prof Svcs-Not Spec'd","alt":"6343118"},{"0":"48175","name":"ICE DATA PRICING & REFERENCE DATA LLC ","invoice":"2026-05-06","gross":"4462.5000","status":"Paid","description":"Prof Svcs-Not Spec'd","alt":"6343118"},{"0":"48910","name":"RELX INC DBA LEXISNEXIS ","invoice":"2026-05-31","gross":"3545.0000","status":"Processing","description":"Prof Svcs-Not Spec'd","alt":"6343118"}]